lz20c.cp37-win_amd64.pyd
lz77c.cp37-win_amd64.pyd
lzw_c.cp37-win_amd64.pyd
lzhw/__init__.py
lzhw/compress_util.py
lzhw/huffman_coding.py
lzhw/lz20c.c
lzhw/lz20c.pyx
lzhw/lz77c.c
lzhw/lz77c.pyx
lzhw/lz78.py
lzhw/lzhw_alg.py
lzhw/lzhw_df.py
lzhw/lzw_c.c
lzhw/lzw_c.pyx
lzhw/para_util.py
lzhw/pq.py
lzhw/util.py
lzhw-1.1.17.dist-info/LICENSE
lzhw-1.1.17.dist-info/METADATA
lzhw-1.1.17.dist-info/WHEEL
lzhw-1.1.17.dist-info/top_level.txt
lzhw-1.1.17.dist-info/RECORD
