Metadata-Version: 2.1
Name: lzhw
Version: 1.1.17
Summary: Compression suite for data frames and tabular data files, csv, excel etc.
Home-page: https://github.com/MNoorFawi/lzhw
Author: Muhammad N. Fawi
Author-email: m.noor.fawi@gmail.com
License: MIT
Platform: UNKNOWN
Classifier: License :: OSI Approved :: MIT License
Classifier: Programming Language :: Python :: 3
Classifier: Programming Language :: Python :: 3.7
Classifier: Programming Language :: Python :: 3.8
Requires-Dist: pandas
Requires-Dist: tqdm
Requires-Dist: numpy
Requires-Dist: joblib
